mosspilot/__init__.py
mosspilot/cli.py
mosspilot/core/__init__.py
mosspilot/core/base/__init__.py
mosspilot/core/base/decorators.py
mosspilot/core/base/fixtures.py
mosspilot/core/base/test_base.py
mosspilot/core/config/__init__.py
mosspilot/core/config/env_manager.py
mosspilot/core/config/settings.py
mosspilot/core/database/__init__.py
mosspilot/core/database/connection.py
mosspilot/core/database/models.py
mosspilot/core/database/operations.py
mosspilot/core/monitoring/__init__.py
mosspilot/core/monitoring/logger.py
mosspilot/core/monitoring/metrics.py
mosspilot/core/reporting/__init__.py
mosspilot/core/reporting/html_reporter.py
mosspilot/modules/__init__.py
mosspilot/modules/api/__init__.py
mosspilot/modules/api/assertions.py
mosspilot/modules/api/client.py
mosspilot/modules/api/utils.py
mosspilot/modules/performance/__init__.py
mosspilot/modules/performance/locust_tasks.py
mosspilot/modules/performance/metrics.py
mosspilot/modules/ui/__init__.py
mosspilot/modules/ui/actions.py
mosspilot/modules/ui/browser.py
mosspilot-0.1.1.dist-info/METADATA
mosspilot-0.1.1.dist-info/WHEEL
mosspilot-0.1.1.dist-info/entry_points.txt
mosspilot-0.1.1.dist-info/licenses/LICENSE
mosspilot-0.1.1.dist-info/RECORD
