Metadata-Version: 2.4
Name: mosspilot
Version: 0.1.1
Summary: 全功能自动化测试框架 - 支持API/UI/性能测试
Project-URL: Homepage, https://github.com/mosspilot-team/mosspilot
Project-URL: Documentation, https://mosspilot.readthedocs.io
Project-URL: Repository, https://github.com/mosspilot-team/mosspilot.git
Project-URL: Issues, https://github.com/mosspilot-team/mosspilot/issues
Project-URL: Changelog, https://github.com/mosspilot-team/mosspilot/blob/main/CHANGELOG.md
Author-email: MossPilot Team <team@mosspilot.com>
License: Apache-2.0
License-File: LICENSE
Keywords: api,automation,framework,mosspilot,performance,pytest,testing,ui
Classifier: Development Status :: 3 - Alpha
Classifier: Framework :: Pytest
Classifier: Intended Audience :: Developers
Classifier: License :: OSI Approved :: Apache Software License
Classifier: Operating System :: OS Independent
Classifier: Programming Language :: Python :: 3
Classifier: Programming Language :: Python :: 3.13
Classifier: Topic :: Software Development :: Quality Assurance
Classifier: Topic :: Software Development :: Testing
Requires-Python: >=3.13
Requires-Dist: alembic>=1.13.0
Requires-Dist: allure-pytest>=2.13.0
Requires-Dist: build>=1.3.0
Requires-Dist: httpx>=0.25.0
Requires-Dist: jinja2>=3.1.0
Requires-Dist: locust>=2.17.0
Requires-Dist: loguru>=0.7.0
Requires-Dist: playwright>=1.40.0
Requires-Dist: pydantic>=2.5.0
Requires-Dist: pytest-asyncio>=0.23.0
Requires-Dist: pytest-html>=4.0.0
Requires-Dist: pytest-xdist>=3.0.0
Requires-Dist: pytest>=8.0.0
Requires-Dist: pyyaml>=6.0.0
Requires-Dist: rich>=13.0.0
Requires-Dist: sqlalchemy>=2.0.0
Requires-Dist: twine>=6.2.0
Requires-Dist: typer>=0.9.0
Provides-Extra: dev
Requires-Dist: black>=23.0.0; extra == 'dev'
Requires-Dist: flake8>=6.0.0; extra == 'dev'
Requires-Dist: isort>=5.12.0; extra == 'dev'
Requires-Dist: mypy>=1.7.0; extra == 'dev'
Requires-Dist: pre-commit>=3.5.0; extra == 'dev'
